{
  "baseunit": "SquareMeter",
  "operators": {
    "mul": [
      {
        "other": "Length",
        "result": "Volume"
      }
    ],
    "div": [
      {
        "other": "Length",
        "result": "Length"
      }
    ]
  },
  "name": "Area",
  "units": [
    {
      "factor": "1e6",
      "name": "SquareKilometer",
      "abbreviation": "km\u00b2"
    },
    {
      "factor": "1e4",
      "name": "Hectare",
      "abbreviation": "ha"
    },
    {
      "factor": "1",
      "name": "SquareMeter",
      "abbreviation": "m\u00b2"
    },
    {
      "factor": "1e-2",
      "name": "SquareDecimeter",
      "abbreviation": "dm\u00b2"
    },
    {
      "factor": "1e-4",
      "name": "SquareCentimeter",
      "abbreviation": "cm\u00b2"
    },
    {
      "factor": "1e-6",
      "name": "SquareMillimeter",
      "abbreviation": "mm\u00b2"
    },
    {
      "factor": "1e-12",
      "name": "SquareMicrometer",
      "abbreviation": "\u03bcm\u00b2"
    },
    {
      "factor": "6.4516e-4",
      "name": "SquareInch",
      "abbreviation": "in\u00b2"
    },
    {
      "factor": "9.2903e-2",
      "name": "SquareFoot",
      "abbreviation": "ft\u00b2"
    },
    {
      "factor": "8.36127e-1",
      "name": "SquareYard",
      "abbreviation": "yd\u00b2"
    },
    {
      "factor": "2.59e6",
      "name": "SquareMile",
      "abbreviation": "mi\u00b2"
    },
    {
      "factor": "4046.85642",
      "name": "Acre",
      "abbreviation": "ac"
    }
  ]
}